pyIsoFit/__init__.py
pyIsoFit/_version.py
pyIsoFit/core/__init__.py
pyIsoFit/core/example.py
pyIsoFit/core/exceptions.py
pyIsoFit/core/fitting.py
pyIsoFit/core/model_dicts.py
pyIsoFit/core/model_equations.py
pyIsoFit/core/model_fit_def.py
pyIsoFit/core/utility_functions.py
pyIsoFit/ext_models/__init__.py
pyIsoFit/ext_models/ext_dsl.py
pyIsoFit/models/__init__.py
pyIsoFit/models/dsl.py
pyIsoFit/models/generic.py
pyIsoFit/models/henry.py
pyIsoFit-0.0.5.dist-info/LICENCE.txt
pyIsoFit-0.0.5.dist-info/METADATA
pyIsoFit-0.0.5.dist-info/WHEEL
pyIsoFit-0.0.5.dist-info/top_level.txt
pyIsoFit-0.0.5.dist-info/RECORD
