Metadata-Version: 2.1
Name: pyIsoFit
Version: 0.0.5
Summary: Package for The Fitting of Adsorption Isotherms and Prediction of Multi-component Isotherms
Home-page: UNKNOWN
Author: Dominik Pantak
License: UNKNOWN
Platform: UNKNOWN
Classifier: Programming Language :: Python :: 3
Classifier: License :: OSI Approved :: MIT License
Classifier: Operating System :: OS Independent
Requires-Python: >=3.6
License-File: LICENCE.txt
Requires-Dist: lmfit (==1.*)
Requires-Dist: scipy (==1.*)
Requires-Dist: pandas (==1.*)
Requires-Dist: matplotlib (==3.*)
Requires-Dist: numpy (==1.*)
